reproduce_wem_taxonomy/__init__.py
reproduce_wem_taxonomy/collect_relevant_publications.py
reproduce_wem_taxonomy/export_database.py
reproduce_wem_taxonomy/fish_wem_taxonomy.py
reproduce_wem_taxonomy/share.py
reproduce_wem_taxonomy-2020.1.29.dist-info/METADATA
reproduce_wem_taxonomy-2020.1.29.dist-info/WHEEL
reproduce_wem_taxonomy-2020.1.29.dist-info/top_level.txt
reproduce_wem_taxonomy-2020.1.29.dist-info/RECORD
