Metadata-Version: 2.1
Name: reproduce-wem-taxonomy
Version: 2020.1.29
Summary: Reproduce the database of use cases for WEMs.
Home-page: https://github.com/momits/pubfisher/
Author: Moritz Renftle
Author-email: wem-taxonomy@momits.de
License: UNKNOWN
Platform: UNKNOWN
Classifier: Programming Language :: Python :: 3
Classifier: License :: OSI Approved :: MIT License
Classifier: Operating System :: OS Independent
Requires-Python: >=3.7
Requires-Dist: pubfisher
Requires-Dist: typeguard
Requires-Dist: psycopg2
